.DS_Store
OPTAMI/.DS_Store
OPTAMI/__init__.py
OPTAMI/accelerations/__init__.py
OPTAMI/accelerations/_supplemetrary.py
OPTAMI/accelerations/nata.py
OPTAMI/accelerations/near_optimal_tensor_acceleration.py
OPTAMI/accelerations/nesterov_acceleration.py
OPTAMI/accelerations/optimal.py
OPTAMI/accelerations/prox_point_segment_search.py
OPTAMI/first_order/__init__.py
OPTAMI/first_order/gradient_descent.py
OPTAMI/first_order/similar_triangles.py
OPTAMI/second_order/__init__.py
OPTAMI/second_order/basic_tensor_method.py
OPTAMI/second_order/cubic_regularized_newton.py
OPTAMI/second_order/damped_newton.py
OPTAMI/utils/__init__.py
OPTAMI/utils/derivatives.py
OPTAMI/utils/fit.py
OPTAMI/utils/line_search.py
OPTAMI/utils/subproblem_solver.py
OPTAMI/utils/tuple_to_vec.py
tests/__init__.py
tests/test_universal_logreg.py
tests/first_order/__init__.py
tests/first_order/test_similar_triangles.py
tests/others/__init__.py
tests/others/test_line_search.py
tests/third_order/__init__.py
tests/third_order/test_methods_steps_third.py
OPTAMI-0.0.2.dist-info/LICENSE
OPTAMI-0.0.2.dist-info/METADATA
OPTAMI-0.0.2.dist-info/WHEEL
OPTAMI-0.0.2.dist-info/top_level.txt
OPTAMI-0.0.2.dist-info/RECORD
