Metadata-Version: 2.1
Name: OPTAMI
Version: 0.0.2
Summary: Second-Order PyTorch Optimizers
Home-page: https://github.com/OPTAMI/OPTAMI
Author: Dmitry Kamzolov
Author-email: kamzolov.opt@gmail.com
Keywords: python,pytorch,optimization,optimizer
Classifier: Programming Language :: Python :: 3
Classifier: Operating System :: OS Independent
Requires-Python: >=3.6
License-File: LICENSE
